README.txt
setup.cfg
setup.py
collective/__init__.py
collective.geo.mapcontent.egg-info/PKG-INFO
collective.geo.mapcontent.egg-info/SOURCES.txt
collective.geo.mapcontent.egg-info/dependency_links.txt
collective.geo.mapcontent.egg-info/entry_points.txt
collective.geo.mapcontent.egg-info/namespace_packages.txt
collective.geo.mapcontent.egg-info/not-zip-safe
collective.geo.mapcontent.egg-info/paster_plugins.txt
collective.geo.mapcontent.egg-info/requires.txt
collective.geo.mapcontent.egg-info/top_level.txt
collective/geo/__init__.py
collective/geo/mapcontent/README.txt
collective/geo/mapcontent/__init__.py
collective/geo/mapcontent/config.py
collective/geo/mapcontent/configure.zcml
collective/geo/mapcontent/profiles.zcml
collective/geo/mapcontent/skins.zcml
collective/geo/mapcontent/browser/__init__.py
collective/geo/mapcontent/browser/configure.zcml
collective/geo/mapcontent/content/__init__.py
collective/geo/mapcontent/content/configure.zcml
collective/geo/mapcontent/content/mapcontent.py
collective/geo/mapcontent/interfaces/__init__.py
collective/geo/mapcontent/interfaces/mapcontent.py
collective/geo/mapcontent/locales/rebuild.sh
collective/geo/mapcontent/portlets/__init__.py
collective/geo/mapcontent/portlets/configure.zcml
collective/geo/mapcontent/profiles/default/factorytool.xml
collective/geo/mapcontent/profiles/default/metadata.xml
collective/geo/mapcontent/profiles/default/portlets.xml
collective/geo/mapcontent/profiles/default/rolemap.xml
collective/geo/mapcontent/profiles/default/skins.xml
collective/geo/mapcontent/profiles/default/types.xml
collective/geo/mapcontent/profiles/default/types/Map_Content.xml
collective/geo/mapcontent/skins/geo_mapcontent/geo_mapcontent_view.pt
collective/geo/mapcontent/tests/__init__.py
collective/geo/mapcontent/tests/base.py
collective/geo/mapcontent/tests/test_doctest.py
docs/HISTORY.txt
docs/INSTALL.txt
docs/LICENSE.GPL
docs/LICENSE.txt