Metadata-Version: 1.0
Name: collective.geo.mapcontent
Version: 0.1
Summary: Map content type for collective.geo (use c.g/MapWidget and c.g.openlayers)
Home-page: http://pypi.python.org/pypi/collective.geo.mapcontent
Author: Mathieu PASQUET <kiorky@cryptelium.net>
Author-email: kiorky@cryptelium.net
License: GPL
Platform: UNKNOWN
Classifier: Framework :: Plone
Classifier: Programming Language :: Python
Classifier: Topic :: Software Development :: Libraries :: Python Modules
